{
  "domain": {
    "term": {
      "convenes": "Invocaciones",
      "convene_url": "URL de invocación",
      "pulls": "Invocaciones",
      "astrites": "Astritas",
      "wuthering_waves": "Wuthering Waves",
      "pull_history": "Historial de invocación",
      "pull_num": "Núm.",
      "item": "Objeto",
      "pity": "Pity",
      "rarity": "Rareza",
      "date_received": "Fecha",
      "recent_convenes": "Invocaciones recientes",
      "resonator": "Resonador",
      "weapon": "Arma"
    },
    "phrase": {
      "import_data": "Importar datos",
      "import_data_description": "Usa tus datos exportados previamente y guárdalos en tu navegador",
      "banner_list": "Lista de banners",
      "no_pulls_yet": "Aún no se ha invocado",
      "rarity_pulls": "{num}✦ Invocaciones",
      "num_pity": "{num}✦ Pity",
      "total_pulls": "Invocaciones Totales",
      "total_pulls_responsive": "Invocaciones <span>Totales</span>",
      "total_astrites_responsive": "Astritas <span>totales</span>"
    },
    "name": {
      "items": {
        "Rover-Havoc": "Errante-Destrucción",
        "Rover-Spectro": "Errante-Espectro",
        "Rover-Aero": "Errante-Aero",
        "Aalto": "Aalto",
        "Augusta": "Augusta",
        "Baizhi": "Baizhi",
        "Brant": "Brant",
        "Buling": "Buling",
        "Calcharo": "Calcharo",
        "Carlotta": "Carlotta",
        "Cartethyia": "Cartethyia",
        "Camellya": "Camellya",
        "Changli": "Changli",
        "Chisa": "Chisa",
        "Chixia": "Chixia",
        "Ciaccona": "Ciaccona",
        "Danjin": "Danjin",
        "Encore": "Encore",
        "Galbrena": "Galbrena",
        "Iuno": "Iuno",
        "Jianxin": "Jianxin",
        "Jinhsi": "Jinhsi",
        "Jiyan": "Jiyan",
        "Lingyang": "Lingyang",
        "Lumi": "Lumi",
        "Lupa": "Lupa",
        "Lynae": "Lynae",
        "Mornye": "Mornye",
        "Mortefi": "Mortefi",
        "Phoebe": "Phoebe",
        "Phrolova": "Phrolova",
        "Qiuyuan": "Qiuyuan",
        "Roccia": "Roccia",
        "Sanhua": "Sanhua",
        "Shorekeeper": "La Guardiana de la Orilla",
        "Taoqi": "Taoqi",
        "Verina": "Verina",
        "Yangyang": "Yangyang",
        "Yinlin": "Yinlin",
        "Yuanwu": "Yuanwu",
        "Zhezhi": "Zhezhi",
        "Xiangli Yao": "Xiangli Yao",
        "Youhu": "Youhu",
        "Zani": "Zani",
        "Abyss Surges": "Oleadas del Abismo",
        "Aether Strike": "Golpe de Éter",
        "Ages of Harvest": "Eras de Cosecha",
        "Amity Accord": "Acuerdo de Amistad",
        "Aureate Zenith": "Cenit Áureo",
        "Autumntrace": "Rastro de Otoño",
        "Beguiling Melody": "Melodía Cautivadora",
        "Blazing Brilliance": "Brillo Abrasador",
        "Blazing Justice": "Veredicto del destello",
        "Boson Astrolabe": "Boson Astrolabe",
        "Bloodpact's Pledge": "Pacto de sangre",
        "Broadblade of Night": "Mandoble de la Noche",
        "Broadblade of Voyager": "Mandoble del Viajero",
        "Broadblade#41": "Mandoble#41",
        "Cadenza": "Cadenza",
        "Call of the Abyss": "Llamada del abismo",
        "Cantarella": "Cantarella",
        "Celestial Spiral": "Espiral celestial",
        "Commando of Conviction": "Comando de Convicción",
        "Comet Flare": "Llamarada de Cometa",
        "Cosmic Ripples": "Ondas Cósmicas",
        "Dauntless Evernight": "Noche Intrépida",
        "Defier's Thorn": "Espina de la Desafiadora",
        "Discord": "Disonancia",
        "Emerald of Genesis": "Esmeralda del Génesis",
        "Emerald Sentence": "Sentencia Esmeralda",
        "Fables of Wisdom": "Fábulas de sabiduría",
        "Feather Edge": "Filo de Pluma",
        "Fusion Accretion": "Acreción de fusion",
        "Gauntlets of Night": "Brazales de la Noche",
        "Gauntlets of Voyager": "Brazales del Viajero",
        "Gauntlets#21D": "Brazales#21D",
        "Guardian Broadblade": "Mandoble de Guardián",
        "Guardian Gauntlets": "Brazales de Guardián",
        "Guardian Pistols": "Pistolas de Guardián",
        "Guardian Rectifier": "Rectificador de Guardián",
        "Guardian Sword": "Espada de Guardián",
        "Helios Cleaver": "Espada de Helios",
        "Hollow Mirage": "Espejismo Hueco",
        "Jinzhou Keeper": "Guardián de Jinzhou",
        "Kumokiri": "Kumokiri",
        "Laser Shearer": "Laser Shearer",
        "Legend of Drunken Hero": "Crónica del héroe ebrio",
        "Lethean Elegy": "Elegía letea",
        "Lunar Cutter": "Cortador Lunar",
        "Lumingloss": "Lumingloss",
        "Luminous Hymn": "Himno luminoso",
        "Lustrous Razor": "Navaja Brillante",
        "Lux & Umbra": "Lux & Umbra",
        "Marcato": "Marcato",
        "Meditations on Mercy": "Meditaciones de la piedad",
        "Moongazer's Sigil": "Sigilo de la Miraluna",
        "Novaburst": "Novestallido",
        "Ocean's Gift": "Regalo del mar",
        "Originite: Type I": "Originite: Tipo I",
        "Originite: Type II": "Originite: Tipo II",
        "Originite: Type III": "Originite: Tipo II",
        "Originite: Type IV": "Originite: Tipo IV",
        "Originite: Type V": "Originite: Tipo V",
        "Overture": "Obertura",
        "Phasic Homogenizer": "Phasic Homogenizer",
        "Pistols of Night": "Pistolas de la noche",
        "Pistols of Voyager": "Pistolas del viajero",
        "Pistols#26": "Pistolas #26",
        "Pulsation Bracer": "Pulsation Bracer",
        "Radiance Cleaver": "Radiance Cleaver",
        "Radiant Dawn": "Amanecer Radiante",
        "Rectifier of Night": "Rectificador de la noche",
        "Rectifier of Voyager": "Rectificador del viajero",
        "Rectifier#25": "Rectificador #25",
        "Red Spring": "Primavera roja",
        "Relativistic Jet": "Chorro relativista",
        "Romance in Farewell": "Romance de la despedida",
        "Rover: Spectro": "Errante: Espectro",
        "Rover: Havoc": "Errante: Destrucción",
        "Rover: Aero": "Errante: Aero",
        "Somnoire Anchor": "Ancla de Somnolencia",
        "Solar Flame": "Llama Solar",
        "Spectrum Blaster": "Spectrum Blaster",
        "Starfield Calibrator": "Starfield Calibrator",
        "Static Mist": "Niebla estática",
        "Stellar Symphony": "Sinfonia estelar",
        "Stonard": "Stonard",
        "Stringmaster": "Maestro de cuerdas",
        "Sword of Night": "Espada de la noche",
        "Sword of Voyager": "Espada del viajero",
        "Sword#18": "Espada #18",
        "The Last Dance": "Último baile",
        "Thunderflare Dominion": "Trueno de la Corona",
        "Thunderbolt": "Rayo",
        "Tragicomedy": "Tragicomedia",
        "Training Broadblade": "Mandoble de entrenamiento",
        "Training Gauntlets": "Brazales de entrenamiento",
        "Training Pistols": "Pistolas de entrenamiento",
        "Training Rectifier": "Rectificador de entrenamiento",
        "Training Sword": "Espada de entrenamiento",
        "Tyro Broadblade": "Mandoble de principiante",
        "Tyro Gauntlets": "Brazales de principiante",
        "Tyro Pistols": "Pistolas de principiante",
        "Tyro Rectifier": "Rectificador de principiante",
        "Tyro Sword": "Espada de principiante",
        "Undying Flame": "Llama eterna",
        "Unflickering Valor": "Valor inquebrantable",
        "Variation": "Variación",
        "Verdant Summit": "Cumbre verde",
        "Rime-Draped Sprouts": "Brotes escarchados",
        "Verity's Handle": "Mango de la verdad",
        "Augment": "Consonante sorda",
        "Endless Collapse": "Colapso interminable",
        "Waltz in Masquerade": "Vals enmascarado",
        "Waning Redshift": "Corrimiento al rojo",
        "Wildfire Mark": "Marca de fuego salvaje",
        "Woodland Aria": "Aria del bosque",
        "Whispers of Sirens": "Susurros de sirenas"
      },
      "banners": {
        "Featured Resonator": "Resonador destacado",
        "Featured Character": "Resonador destacado",
        "Featured Weapon": "Arma destacada",
        "Permanent Resonator": "Resonador permanente",
        "Permanent Weapon": "Arma permanente",
        "Novice Convene": "Invocación de novato",
        "Beginner's Choice": "Selección de novato",
        "Selector Ticket": "Boleto selector",
        "Tidal Chorus": "Coro de Marea",
        "Winter Brume": "Bruma Invernal",
        "Utterance of Marvels": "Declaración de maravillas",
        "Beginner's Choice Convene": "Invocación de elección de novato",
        "Giveback Event Convene": "Evento de gratitud",
        "New Voyage Weapon": "Arma del Nuevo Viaje",
        "New Voyage Resonator": "Resonador del Nuevo Viaje"
      }
    }
  },
  "common": {
    "message": {
      "error": {
        "generic_title": "Ocurrió un error",
        "no_banner": "No se ha encontrado banners.",
        "relogin_to_sync": "Por favor inicia sesión de nuevo para sincronizar.",
        "no_auth_scopes": "No estás autorizado a subir en Google Drive.",
        "auth_session_expired": "Tu sesión ha expirado.",
        "invalid_input_format": "Los datos introducidos son invalidos",
        "unable_to_parse": "No podemos analizar tus datos",
        "unable_to_parse_remote_data": "No podemos analizar tus datos remotos",
        "unable_to_parse_profile_data": "Esto es solo para los datos del perfil. Usa el otro botón de importar para los datos del historial de tiradas.",
        "download_failed": "La descarga ha fallado",
        "client_log_required": "¡Necesitas subir un archivo Client.log!",
        "cannot_find_convene_url": "No pudimos encontrar tu URL de invocación",
        "cannot_find_convene_url_description": "Asegúrate de que tu Client.log se actualiza cuando abres tu historial. En caso contrario, consulte la sección de solución de problemas para obtener ayuda.",
        "convene_url_expired": "Tu URL probablemente ha expirado.",
        "use_valid_player_id": "Debes usar un ID de jugador activo válido",
        "no_profile_to_download": "No hay perfil para descargar.",
        "no_pulls_to_download": "No hay invocaciones que descargar.",
        "need_to_upload_specific_file": "¡Tienes que subir un {file}!",
        "sync_no_pulls_to_upload": "No tienes invocaciones que subir.",
        "sync_unavailable": "No pudimos sincronizar en estos momentos.",
        "sync_no_remote_data_to_download": "No tienes ningunos datos remotos que descargar.",
        "incorrect_input_file_description": "¡Esto es SOLO para el nuevo formato de importación del historial de invocaciones!",
        "files_no_upload": "No se subió ningún archivo.",
        "files_max_upload_num": "Solo puedes subir hasta {num} archivo(s).",
        "files_has_oversize_limit_num": "Algunos archivos superan el límite de tamaño de {num}MB.",
        "inventory_item_does_not_exist": "¡Este objeto no existe!",
        "planner_insufficient_materials": "Materiales insuficientes.",
        "you_must_use_a_non_guest_profile_to_export_pull_history": "Debe utilizar un perfil que no sea de invitado para exportar tu historial de invocaciones",
        "failed_to_unlink_email": "Error al desvincular tu correo electrónico",
        "failed_to_fetch_pulls_from_database": "No se pudo obtener las extracciones de nuestra base de datos",
        "an_error_occured_while_merging_your_data": "Ha ocurrido un error al combinar tus datos",
        "your_email_must_be_linked_to_import_pulls": "Tu correo electrónico debe estar vinculado para importar las invocaciones",
        "your_email_must_be_linked_to_import_pulls_description": "Por favor, inicia sesión y vincula tu ID de jugador primero."
      },
      "info": {
        "connecting_google": "Intentando conectar a Google Drive",
        "sign_in_first": "Inicia sesión primero",
        "already_linked": "Ya vinculado",
        "enable_email_link": "Habilita la vinculación del correo",
        "sign_in_to_sync": "Inicia sesión para sincronizar",
        "loading": "Cargando...",
        "import_loading": "Importando registros del gacha...",
        "import_loading_description": "¡Esto no debería tardar mucho!",
        "scroll_for_more": "Baja para más",
        "no_filters": "no se ha seleccionado ningún filtro",
        "no_records": "no hay registros que mostrar",
        "no_pulls_yet": "Aún no se ha invocado",
        "no_pulls_found_in_google_drive": "No se ha encontrado ninguna invocacion en Google Drive",
        "no_banner_luck_stats": "este banner no tiene estadísticas de suerte",
        "max_recent_pulls_disclaimer": "Este resumen solo muestra hasta {num} invocaciones recientes.",
        "pull_more_to_unlock": "Invoca más para desbloquear",
        "pull_more_to_view_statistics": "Necesitas más invocaciones para ver las estadísticas",
        "download_will_start_shortly": "Tu descarga comenzará en breve.",
        "sync_already_synced": "Tus datos ya están sincronizados.",
        "google_drive_last_updated_at": "Google Drive se actualizó el {date}",
        "nothing_to_sync": "No hay nada que sincronizar en este momento.",
        "sync_creating_file_in_google": "Creando {fileName} en Google Drive...",
        "sync_updating_remote_file": "Actualizando la copia remota para {fileName}...",
        "planner_edited_plan_for_name": "Plan {name} editado.",
        "unlinking_your_email": "Desvinculando tu correo...",
        "importing_cloud_data": "Importando datos en la nube de nuestra base de datos...",
        "this_may_take_some_time_if_you_have_a_lot_of_data": "Esto puede tardar un poco si tienes muchos datos o si el sitio está ocupado.",
        "no_new_pulls_found_after_importing": "No se encontraron nuevas invocaciones después de importar."
      },
      "success": {
        "successfully_imported_achievements": "Se han importado tus logros exitosamente.",
        "successfully_imported_gacha_records": "Se han importado tu historial de invocación exitosamente.",
        "successfully_imported_num_new_pulls": "Importados con éxito {num} nuevas extracciones.",
        "successfully_imported_profile": "Se ha importado tu perfil de usuario exitosamente.",
        "the_import_was_successful": "¡La importación fue un éxito!",
        "successfully_imported_gacha_records_redirecting": "Redirigiendo a tu tracker.",
        "create_profile": "Se ha creado un perfil exitosamente para {playerId}.",
        "delete_pulls": "Se han borrado todas las invocaciones de {playerId}.",
        "delete_profiles": "Se ha eliminado todos los perfiles de usuario exitosamente.",
        "sync_successfully_downloaded_remote_data": "Se ha descargado los datos remotos exitosamente.",
        "sync_successfully_created_remote_data": "Se ha creado {fileName} en Google Drive exitosamente.",
        "sync_success": "Sincronización exitosa.",
        "sync_success_updated_remote_file": "Actualizado la copia remota para {fileName}.",
        "planner_successfully_completed_plan_for_name": "¡Plan {name} completado exitosamente!",
        "planner_successfully_created_plan_for_name": "Se ha creado exitosamente el plan {name}.",
        "successfully_unlinked_email": "Se desvinculó correctamente tu correo electrónico"
      },
      "warn": {
        "this_cannot_be_undone": "¡Esta acción no se puede deshacer!",
        "disable_auto_profile_sync": "For your safety, will also disable automatic profile sync!",
        "this_does_not_include_your_pulls": "¡Esto no incluye tus invocaciones!",
        "planner_removed_plan_for_name": "Plan {name} eliminado."
      }
    },
    "form": {
      "banner_select_placeholder": "Elegir banner",
      "banner_search_placeholder": "Buscar banner...",
      "search": "Buscar",
      "search_placeholder": "Buscando algo...",
      "search_reset": "Reiniciar buscador",
      "your_player_id_placeholder": "Tu ID de jugador de nueve dígitos (ej. 123456789)",
      "your_player_id_validation": "Tu ID de jugador de nueve dígitos debe empezar por 1, 5, 6, 7, 8 o 9",
      "type_to_confirm": "Escriba <strong></strong> para confirmar",
      "file_input": "Haz clic para subir o arrastra y suelta",
      "accepted_formats": "Formatos aceptados: {formats}",
      "select_profile_placeholder_empty": "No se han encontrado perfiles",
      "select_profile_placeholder_inactive": "Elige un perfil activo",
      "filters": "Filtros",
      "rows_per_page": "Filas por página",
      "planner_previous_must_be_between_min_max": "El nivel anterior debe estar entre {min} y {max}.",
      "planner_new_must_be_between_min_max": "El nivel nuevo debe de estar entre {min} y {max}."
    },
    "button": {
      "go_home": "Ir a la página principal",
      "switch_theme": "Cambiar tema",
      "sign_in_google": "Iniciar sesión con Google",
      "log_out": "Cerrar sesión",
      "import_history": "Importar historial",
      "filter_by_rarity_num": "Filtrar por rareza {num}",
      "import": "Importar",
      "export_json": "Exportar como JSON",
      "view_pull_history": "Ver historial de invocaciones",
      "sync_your_data": "Sincroniza tus datos",
      "trigger_sync": "Sincronizar",
      "support_us": "Apóyanos",
      "create_profile": "Crear perfil",
      "remind_me_later": "Recuérdamelo más tarde",
      "delete": "Eliminar",
      "confirm": "Confirmar",
      "cancel": "Cancelar",
      "download": "Descargar",
      "import_from_file": "Importar desde archivo",
      "upload_to_google": "Subir a Google",
      "download_from_google": "Descargar desde Google",
      "reset_tag_filters": "Restablecer los filtros de las etiquetas",
      "complete": "Completar",
      "hide": "Ocultar",
      "show": "Mostrar",
      "edit": "Editar",
      "view_details": "Ver detalles"
    },
    "time": {
      "all_time": "Todos los tiempos",
      "last_num_days": "Últimos {num} días",
      "invalid_date": "Fecha inválida",
      "local_time": "Hora local",
      "server_time": "Hora del servidor",
      "ends_in": "Termina en {timeLeft}",
      "starts_in": "Empieza en {timeLeft}",
      "time_left": "Quedan {timeLeft}",
      "event_has_ended": "El evento ha terminado",
      "your_local_time": "Tu hora local",
      "current_server_time": "Tiempo actual del servidor",
      "resets_in": "Resets en",
      "some_time": "algún tiempo",
      "months": {
        "January": "Enero",
        "February": "Febrero",
        "March": "Marzo",
        "April": "Abril",
        "May": "Mayo",
        "June": "Junio",
        "July": "Julio",
        "August": "Agosto",
        "September": "Septiembre",
        "October": "Octubre",
        "November": "Noviembre",
        "December": "Diciembre"
      },
      "days_short": {
        "Mo": "Lu",
        "Tu": "Ma",
        "We": "Mi",
        "Th": "Ju",
        "Fr": "Vi",
        "Sa": "Sa",
        "Su": "Do"
      }
    },
    "other": {
      "alert": "Alerta",
      "name": "Nombre",
      "guest": "Invitado",
      "america": "América",
      "europe": "Europa",
      "asia_sea_regions": "Asia, SEA, TW/HK/MO",
      "completed": "Completado",
      "incomplete": "Incompleto",
      "completion": "Estado",
      "all": "Todo",
      "hidden": "Oculto",
      "visible": "Visible",
      "local_data": "Datos locales",
      "google_drive": "Google Drive",
      "from_file": "Desde archivo",
      "edit_on_github": "Editar está página en GitHub",
      "social_discord_cta": "Únete a nuestro servidor de Discord",
      "social_x_cta": "Síguenos en X",
      "social_reddit_cta": "Únete a nuestro subreddit",
      "social_github_cta": "Contribuye en GitHub",
      "community": "Comunidad",
      "contact": "Contacto",
      "for_general_inquiries": "Para consultas generales:",
      "for_support": "Para apoyar:",
      "supporters": "Colaboradores",
      "no_particular_order": "sin ningun orden en particular",
      "translators": "Traductores",
      "players": "Jugadores",
      "event": "Evento",
      "ongoing_events": "Eventos en curso",
      "choose_a_method": "Elige un método",
      "automatic": "Automático",
      "manual": "Manual",
      "data": "Datos",
      "preferences": "Preferencias",
      "advanced": "Avanzado",
      "help_translate": "Ayuda a traducir",
      "switch_language": "Cambiar idioma",
      "just_taking_a_look_around": "¿Solo estás echando un vistazo?",
      "the_active_player_profile": "el perfil de jugador activo",
      "privacy": "Privacidad",
      "on": "Encendido",
      "off": "Apagado",
      "toggle": "Activar/desactivar",
      "signed_out": "Sesión cerrada",
      "out_of_sync": "Desincronizado",
      "synced": "Sincronizado",
      "downloads_and_merges": "Descargar y juntar tus invocaciones",
      "image_preview": "Vista previa de imagen",
      "close": "cerrar",
      "portrait_view": "Vista vertical",
      "tile_view": "Visca en mosaico",
      "planner": "Planificador",
      "owned_num": "En posesión: {num}",
      "owned": "Poseído",
      "required_num": "Requerido: {num}",
      "windows": "Windows",
      "macos": "macOS",
      "linux": "Linux",
      "android": "Android",
      "ios": "iOS",
      "ps5": "PS5",
      "download_logs": "Descargar Registros"
    }
  },
  "feature": {
    "support": {
      "troubleshooting": "Solución de problemas",
      "troubleshooting_description": "Si estás experimentando problemas con el importador consulta nuestra guía de solución de problemas aquí.",
      "import": {
        "log_files_missing_q": "El script dice \"install location not found or log files missing\", ¿qué debería hacer?",
        "url_expired_q": "Un error dice \"URL probably expired\", ¿qué debería hacer?",
        "error_while_fetching_q": "Un error dice \"error occured while fetching\", ¿qué debería hacer?",
        "missing_old_pulls_q": "No puedo encontrar mis antiguas invocaciones, ¿dónde están?",
        "support_other_imports_q": "¿Admiten la importación desde otras páginas web o aplicaciones?",
        "ps5_player_import_q": "¿Puedo importar como un jugador de PlayStation 5?",
        "other_q": "Mi problema no aparece aquí, ¿qué debería hacer?"
      }
    },
    "migration": {
      "legacy_migration": "Actualiza tus invocaciones antiguas al nuevo formato aquí",
      "legacy": "Antiguo",
      "legacy_import": "Importar Invocaciones antiguas",
      "legacy_import_alert_title": "Solo para los usuarios de la antigua página web",
      "legacy_import_alert_description": "NO PODEMOS recuperar las invocaciones después del período de caducidad de 6 meses. Este importador de invocaciones antiguas es solo para los usuarios antiguos de WuWa Tracker."
    },
    "layout": {
      "banners": {
        "close_banner": "Cerrar banner"
      },
      "tools": "Herramientas",
      "inventory": "Inventario",
      "guides": "Guías",
      "development": "Desarrollo",
      "system_status": "Estado del sistema",
      "legal": "Legal",
      "partners": "Socios",
      "disclaimer": "Este es un proyecto independiente de fans, no está afiliado ni respaldado por Kuro Games. Todos los activos del juego, contenido y marcas registradas pertenecen a sus respectivos propietarios."
    },
    "error": {
      "oops": "¡Ups!",
      "an_error_occured": "Ocurrió un <highlight>error</highlight>.",
      "join_discord": "Por favor <link>únete a nuestro servidor de Discord</link> para realizar un reporte."
    },
    "achievements": {
      "no_achievements_found": "no se han encontrado logros"
    },
    "tracker": {
      "banner_summary": "Resumen de banner",
      "banner_summary_description": "Selecciona un banner para obtener un resumen de las estadísticas.",
      "luck": {
        "num_luck_rating_title": "Ratio de suerte de {num}✦",
        "top": "{percentile}% superior",
        "bottom": "{percentile}% inferior",
        "luckier": "Tienes más suerte que el {percentile}% de los jugadores",
        "unluckier": "Tienes peor suerte que el {percentile}% de los jugadores",
        "avg_pity": "Pity promedio",
        "avg_pity_description": "¿Cuál es tu promedio de pity de {qualityLevel}-estrellas?",
        "pull_ratio": "Tasa de invocación",
        "pull_ratio_description": "¿Qué porcentaje de todas tus invocaciones fueron {qualityLevel}-estrellas?",
        "coinflip_wins": "50/50 Ganados",
        "coinflip_wins_description": "¿Cuál es el porcentaje de tus invocaciones en el que has ganado el 50/50?",
        "rate_up_wins": "Personajes destacados ganados",
        "rate_up_wins_description": "¿Cómo de seguidos fueron tus invocaciones destacadas?"
      }
    },
    "global_stats": {
      "rarity_pulls": "{num}✦ Invocaciones",
      "rarity_pulls_per_pity": "{num}✦ Invocaciones por Pity",
      "rarity_pulls_per_pity_description": "Mostrando todas las invocaciones por pity",
      "banner_summary_title": "Resumen de banner",
      "banner_summary_description": "Selecciona un banner para obtener un resumen de las estadísticas.",
      "view_your_statistics_responsive": "<span>Ver</span> tus estadísticas",
      "pulls_per_day": "Invocaciones por día",
      "pulls_per_day_description": "Mostrando invocaciones por día y distribución de rareza",
      "pulls_per_rarity": "Invocaciones por rareza",
      "pulls_per_rarity_description": "Mostrando la distribución de rareza",
      "pulls_per_item_description": "Mostrando invocaciones por objeto"
    },
    "settings": {
      "general": {
        "title": "General",
        "site_language": "Idioma del Sitio",
        "site_language_description": "Seleccione el idioma que desea utilizar en el sitio",
        "game_server_timezone": "Zona horaria del servidor del juego",
        "game_server_timezone_description": "Mostrar características relacionadas con el tiempo de acuerdo a la zona horaria del servidor de tu juego"
      },
      "data": {
        "title": "Datos",
        "active_profile": "Perfil Activo",
        "active_profile_description": "Seleccione el perfil activo que desea utilizar en el sitio",
        "import_profile": "Importar Perfil",
        "import_profile_description": "Importar una instantánea de perfil para restaurar o cargar otro perfil",
        "export_profile": "Exportar Perfil",
        "export_profile_description": "Crear una instantánea de los datos de tu perfil activo para compartir o respaldar",
        "import_pull_history": "Importar Historial de Extracción",
        "import_pull_history_description": "Sube tu historial de invocaciones a través de un formato de archivo compatible",
        "export_pull_history": "Exportar Historial de Invocaciones",
        "export_pull_history_description": "Crear una copia de seguridad local de tu historial de extracciones como respaldo",
        "pulls_file_import_dialog_title": "Importar Extracciones Locales",
        "pulls_file_import_dialog_description_supported_files": "Esto acepta archivos JSON <code>wuwatracker-pulls</code> y <code>wuwatracker-convene-history</code> siguiendo el formato de nuestro sitio web.",
        "import_user_profile": "Importar Perfil de Usuario",
        "import_user_profile_dialog_description": "NOTA: Esto solo acepta archivos <code></code> con logros, inventario, y datos del planificador. Usa el otro botón de importación si quieres importar los datos de las invocaciones.",
        "profile_data_will_not_sync_callout_description": "Tus cambios solo se almacenan de manera local y se perderán cuando inicies sesión. Para sincronizar los datos de tu perfil:",
        "profile_data_will_not_sync_callout_sign_in": "<link>Inicia sesión</link> con tu cuenta",
        "profile_data_will_not_sync_callout_link_your_uid": "<link>Vincula tu UID</link> a tu cuenta",
        "profile_data_will_not_sync_callout_select_your_linked_profile": "Selecciona tu perfil vinculado ({sessionPlayerId}) <link>en tus ajustes</link>"
      },
      "connections": {
        "title": "Conexiones",
        "active_email": "Correo activo",
        "active_email_description": "Este es el correo electrónico activo con el que estás conectado actualmente",
        "linked_user_id": "ID de Usuario Vinculado",
        "linked_user_id_description": "Este es el ID de usuario vinculado a tu correo electrónico activo",
        "link_your_email": "Vincula tu correo electrónico",
        "link_your_email_description": "Desbloquea más funciones vinculando tu ID de jugador de Wuthering Waves a tu correo electrónico",
        "unlink_email": "Desvincular correo electrónico",
        "unlink_email_confirm_description": "Perderás el acceso a varias funciones del sitio. Para continuar, por favor escribe <strong></strong> para confirmar.",
        "unlink_email_confirm_input_placeholder": "Escribe {password} para confirmar",
        "player_id": "ID de Jugador",
        "import_to_link": "Importar para Vincular",
        "sign_in_to_link": "Inicia sesión para Vincular",
        "cloud_pull_data": "Datos de Invocaciones en la Nube",
        "cloud_pull_data_description": "Puedes recuperar tus datos de invocaciones de nuestra base de datos si tu correo electrónico está vinculado",
        "recover_pulls": "Recuperar Invocaciones"
      },
      "advanced": {
        "title": "Avanzado",
        "successfully_deleted_active_profile_data": "Se han eliminado correctamente los datos de {activeProfileId}",
        "successfully_deleted_active_profile_pull_data": "Successfully deleted {activeProfileId}'s pull data",
        "website_version": "Versión del Sitio Web",
        "website_version_description": "Actualmente estás usando esta versión del sitio",
        "session_logs": "Registros de Sesión",
        "session_logs_description": "Puedes descargar tus registros con propósitos de depuración",
        "delete_active_profile_data": "Eliminar Datos del Perfil Activo",
        "delete_active_profile_data_description": "Puedes eliminar los datos de perfil del sitio web activo, SÓLO incluyendo todos los datos que no tengan nada que ver con las invocaciones",
        "delete_active_profile_data_confirm_title": "¿Estás seguro de que quieres eliminar los datos de {activeProfileId}?",
        "delete_active_profile_data_confirm_description": "Todos los datos asociados para <strong></strong> se eliminarán. Esta acción no se puede deshacer.",
        "delete_active_profile_pull_data": "Delete Active Profile Pull Data",
        "delete_active_profile_pull_data_description": "You can delete your active profile's pull data from your browser's local storage",
        "delete_active_profile_pull_data_confirm_title": "Are you sure you want to delete {activeProfileId}'s Pull Data?",
        "delete_active_profile_pull_data_confirm_description": "All pull history data for <strong></strong> will be deleted. This action cannot be undone.",
        "delete_active_profile_pull_data_confirm_text": "Delete {activeProfileId}'s Pull Data",
        "profile": "Perfil",
        "type_active_profile_to_confirm": "Escribe {activeProfileId} para confirmar",
        "delete_active_profile_data_confirm_text": "Eliminar los Datos de {activeProfileId}",
        "delete_profile_data": "Eliminar Datos del Perfil",
        "delete_pull_data": "Delete Pull Data",
        "enable_beta_features": "Habilitar Funcionalidades Beta",
        "enable_beta_features_description": "Opta por probar nuevas funciones antes de que sean oficialmente estrenadas"
      }
    },
    "timeline": {
      "choose_server_timezone": "Elija la zona horaria del servidor",
      "choose_server_timezone_description": "Mostrar los tiempos ajustados a tu zona horaria local",
      "timeline_description": "Mira los eventos de Wuthering Waves en tu zona horaria o en otras <link>Zonas Horarias</link>.",
      "reset_timers": {
        "title": "Tiempos de reinicio diario de servidores",
        "description": "Compara tu tiempo local con el tiempo del servidor de Wuthering Waves para planear tu siguiente aventura.",
        "disclaimer": "Las horas de los otros servidores se muestran con su hora local."
      }
    },
    "import": {
      "select_a_method": "Selecciona un método",
      "tutorial_video": "Videotutorial",
      "follow_our_video_tutorial": "Sigue nuestro videotutorial",
      "follow_our_video_tutorial_description": "Este breve video te guiará a través del proceso de importación",
      "follow_this_video_tutorial_by_name": "Sigue este video tutorial de {name}",
      "press_the_import_data_button": "Pulse el botón de \"Importar datos\"",
      "upload_your_client_log_file_here": "Sube aquí tu archivo Client.log",
      "we_will_search_your_logs_and_extract_the_import_url": "Buscaremos en tus registros y extraeremos la URL de importación por ti",
      "logs_not_updating_alert": "URL caducado",
      "logs_not_updating_alert_description": "Desde el 14 de enero del 2025, los usuarios de ordenador han estado experimentando problemas de inicio de sesión debido a una presunta actualización de Kuro Games. Lea nuestra <link>Guía de soporte</link>  para poder solucionar el problema.",
      "first_open_game_history": "Primero, inicia el juego y abre los detalles del historial dentro del juego",
      "open_windows_powershell_and_run_script": "Después, abre Windows Powershell, y pega el siguiente script.",
      "click_the_copy_button": "Haz clic en el botón de copiar a la derecha",
      "powershell_script_disclaimer": "NOTA: El script solo lee los registros del juego para extraer la URL de tu Historial de Invocaciones. Una comprobación SHA256 asegura que el script no haya sido manipulado. Puedes ver el script <link>aquí</link>.",
      "paste_the_url_here": "Pega la URL aquí",
      "paste_the_json_here": "Pega el JSON aquí",
      "go_to_installation_directory": "Ve a la carpeta de instalación del juego",
      "go_to_installation_directory_description": "Clic derecho en tu lanzador de Wuthering Waves y selecciona <code>Abrir la ubicación del archivo</code>. Deberías de ver <code>launcher.exe</code> y un muchos archivos <code>.dll</code>.",
      "search_for_log": "Busca por <code>Client.log</code> y súbelo aquí",
      "airplane_mode": "Airplane Mode",
      "download_ascent": "Descarga y usa Ascent para conseguir tu URL de gacha",
      "download_ascent_description": "Similar to getting your history in Genshin Impact or Honkai Star Rail, follow this <link>guide by Mirai0009</link>to download and use <ascent>Ascent v2.1.6</ascent> to get your URL.",
      "download_ascent_disclaimer": "NOTA: Este método solo es compatible con las versiones de Android 11 y superiores.",
      "download_ascent_troubleshooting": "Si no funciona correctamente, echa un vistazo a la <link>sección de solución de problemas</link>.",
      "ios_follow_tutorial_video": "Sigue nuestro videotutorial",
      "ios_follow_tutorial_video_description": "Similar a conseguir tu historial en Genshin Impact o Honkai Star Rail, sigue este videotutorial para importar tus datos en iOS.",
      "ios_certificate_disclaimer": "NOTA: Debes usar Safari al descargar el archivo de certificado. Otros navegadores como Google Chrome pueden no funcionar.",
      "ps5_credits": "Un agradecimiento especial a <link></link> por compartir la metodología y las imágenes para este tutorial de PlayStation 5.",
      "ps5_press_the_options_button": "Presiona el botón de 'Opciones' en tu mando",
      "ps5_click_on_page_information": "Presiona el botón de 'Información de página'",
      "ps5_enter_your_record_id": "Introduce tu 'player_id' y 'record_id' aquí",
      "open_terminal_and_open_script": "Después, abre tu terminal, y pega el siguiente script:",
      "linux_script_disclaimer": "NOTA: El script solo lee los registros del juego para extraer la URL de tu Historial de Invocaciones. Una comprobación SHA256 asegura que el script no haya sido manipulado. Puedes ver el script <script>aquí</script>. Créditos a <author></author> por compartir su <repo></repo> código.",
      "script_disclaimer": "Nota: El script no edita tus archivos, simplemente extrae la URL de tu Historial de Invocaciones de los registros del juego. Puedes ver el script aquí.",
      "email_link_description": "Esto nos permitirá guardar sus datos en nuestra base de datos y automáticamente hacer una copia de seguridad de sus datos cada vez que importe. Si tu ID de jugador ya está vinculada a otra dirección de correo electrónico, eliminaremos el enlace antiguo y usaremos tu nueva dirección de correo electrónico."
    },
    "planner": {
      "move_up": "Subir",
      "move_down": "Bajar"
    },
    "inventory": {
      "new_plan": "Nuevo plan",
      "add_plan": "Añadir plan",
      "material_summary": "Resumen de Material",
      "no_active_plans": "No tienes ningún plan activo.",
      "nodes_to_unlock": "Nodos a desbloquear",
      "passive_skill": "Habilidad Pasiva",
      "plan_delete_name_confirm": "¿Estás seguro de que quieres eliminar el plan {name}?",
      "no_items_will_be_consumed": "No se consumirán objetos.",
      "attributes": {
        "ascension_level": "Nivel de Ascensión",
        "level": "Nivel",
        "basic_attack": "Ataque normal",
        "resonance_skill": "Habilidad de Resonancia",
        "forte_circuit": "Circuito del Forte",
        "resonance_liberation": "Liberación de Resonancia",
        "intro_skill": "Habilidad Intro"
      },
      "item_tags": {
        "Universal Currency": "Moneda Universal",
        "Skill Upgrade Material": "Material de Mejora de Habilidad",
        "Ascension Material": "Material de Ascensión",
        "Resonator Ascension Material": "Material de Ascensión de Resonador",
        "Resonator EXP Material": "Material de Mejora de Resonador",
        "Weapon and Skill Material": "Material de Armas y Habilidad",
        "Weapon EXP Material": "Material de Mejora de Armas"
      }
    },
    "home_page": {
      "hero_heading": "Tus recursos de Wuthering Waves",
      "hero_cta_button": "Comienza el Seguimiento",
      "keep_up_with_the_latest_news": "Mantente al día con las últimas noticias",
      "quick_links": "Enlaces Rápidos",
      "quick_links_description": "Accede rápidamente a las páginas y funciones importantes",
      "the_curent_events_and_activities": "Los eventos y actividades actuales"
    }
  },
  "metadata": {
    "root": {
      "title": "Aplicación de recursos y compañero de Wuthering Waves",
      "description": "WuWaTracker es el #1 rastreador de invocaciones y contador de piedad para Wuthering Waves. Rastrea tus invocaciones y logros, consulta estadísticas globales, usa nuestro planificador y calculadora de ascensión, y explora nuestras guías, wiki, y articulos para optimizar tu experiencia en Wuthering Waves."
    },
    "achievements": {
      "title": "Logros",
      "page_header": "Sigue tus logros del juego y ve todas las recompensas que has ganado hasta ahora",
      "description": "¡Sigue tus logros en Wuthering Waves e importa y exporta tus datos libremente entre dispositivos! WuWa Tracker es un contador de pity para Wuthering Waves, utilizando los datos más actualizados con estadísticas globales y más. ¡Comparte tus invocaciones con tus amigos y sigue tu cuenta!"
    },
    "tracker": {
      "index": {
        "title": "Seguidor de Invocaciones",
        "page_header": "Mira las estadísticas de tus invocaciones recientes en comparación con otros usuarios de WuWa Tracker.",
        "description": "¡Mira tus estadísticas y tus últimas invocaciones actualizadas en Wuthering Waves! Utiliza paneles preparados para hacer capturas de pantalla y presume ante tus amigos. WuWa Tracker es un contador de pity para Wuthering Waves, utiliza los datos más actualizados con estadísticas globales, y más. ¡Comparte tus invocaciones con tus amigos y sigue tu cuenta!"
      },
      "global": {
        "title": "Estadísticas globales",
        "title_responsive": "Estadísticas <span>globales</span>",
        "description": "¡Mira las estadísticas globales de invocaciones para el banner {currentBanner}, con {currentFeaturedResonator}! Utiliza paneles preparados para hacer capturas de pantalla y presume ante tus amigos. WuWa Tracker es un contador de pity para Wuthering Waves, utiliza los datos más actualizados con estadísticas globales, y más. ¡Comparte tus invocaciones con tus amigos y sigue tu cuenta!",
        "banner_title": "Estadísticas del banner de {name}",
        "banner_description": "Mira las estadísticas globales de invocaciones para el banner {name}. WuWa Tracker es un contador de pity para Wuthering Waves, utilizando los datos más actualizados con estadísticas globales, y más. ¡Comparte tus invocaciones con tus amigos y sigue tu cuenta!"
      }
    },
    "error": {
      "title": "Ocurrió un error",
      "description": "Ocurrió un error al usar WuWa Tracker. Por favor, envía un informe a nuestro servidor de Discord para que podamos solucionarlo rápidamente."
    },
    "import": {
      "title": "Importar Historial de Invocaciones",
      "page_header": "Selecciona tu plataforma y el método preferido para importar tus datos",
      "description": "Sigue nuestro tutorial interactivo para mostrar tus datos de Wuthering Waves y ver tus estadísticas. Soportamos importaciones desde dispositivos PC, Android y iOS con métodos automáticos. WuWa Tracker es un contador de pity para Wuthering Waves que utiliza los datos más actualizados con estadísticas globales, y más. ¡Comparte tus invocaciones con tus amigos y sigue tu cuenta!"
    },
    "not_found": {
      "title": "No Encontrado",
      "description": "Esta página no se encuentra en WuWa Tracker. Por favor, vuelve a la página principal para seguir tu Historial de Invocaciones en Wuthering Waves."
    },
    "privacy_policy": {
      "title": "Políticas de Privacidad",
      "description": "Este documento de políticas de privacidad describe los tipos de información personal que son recibidos y recopilados por WuWa Tracker y cómo son utilizados. WuWa Tracker es un contador de pity para Wuthering Waves que utiliza los datos más actualizados con estadísticas globales, y más."
    },
    "settings": {
      "title": "Configuraciones",
      "page_header": "Gestiona tus preferencias y datos aquí",
      "description": "Sincroniza tus datos a través de Google iniciando sesión. Gestiona tus datos de invocaciones de Wuthering Waves todo en un solo lugar. WuWa Tracker es un contador de pity para Wuthering Waves que utiliza los datos más actualizados con estadísticas globales, y más. ¡Comparte tus invocaciones con tus amigos y sigue tu cuenta!"
    },
    "terms_and_conditions": {
      "title": "Términos y Condiciones",
      "description": "Estos términos y condiciones describen las reglas y regulaciones para el uso del sitio web y servicios de WuWa Tracker."
    },
    "manage_cookies": {
      "title": "Administrar Cookies",
      "description": "Puedes actualizar tus preferencias de cookies en cualquier momento para controlar como recopilamos y usamos tus datos, en cumplimiento de regulaciones de privacidad como el RGPD y la CCPA."
    },
    "timeline": {
      "title": "Cronograma de Eventos",
      "page_header": "Mantente actualizado con los últimos eventos y actividades de Wuthering Waves",
      "description": "Utilizando tu zona horaria local o cualquier zona horaria del servidor de Wuthering Waves, puedes ver cada calendario de banners, eventos del juego, periodos de la Torre de la Adversidad y Profundidades del Reino Ilusorio, todo en un solo lugar. WuWa Tracker es un contador de pity para Wuthering Waves, utilizando los datos más actualizados con estadísticas globales y más. ¡Comparte tus invocaciones con tus amigos y sigue tu cuenta!"
    },
    "wiki": {
      "resonator": {
        "title": "Resonadores",
        "description": "¡Vea la información de los Resonadores de Wuthering Waves y utilice la calculadora de materiales para planificar las mejoras de su Resonador!",
        "page_header": "Mira a todos los Resonadores de Wuthering Waves"
      },
      "item": {
        "title": "Objetos",
        "description": "Ve la información de los objetos de Wuthering Waves, su localización, y sigue tu inventario - todo en un solo lugar. El contador de pity de WuWa Tracker, usando los datos más recientes con las estadísticas globales y más. ¡Comparte tus invocaciones con tus amigos y sigue tu cuenta!",
        "page_header": "Mira todos los Objetos de Wuthering Waves"
      },
      "weapon": {
        "title": "Armas",
        "description": "Ve la información de las armas de Wuthering Waves, sus estadísticas, y sigue tu inventario - todo en un solo lugar. El contador de pity de WuWa Tracker, usando los datos más recientes con las estadísticas globales y más. ¡Comparte tus invocaciones con tus amigos y sigue tu cuenta!",
        "page_header": "Mira a todas las Armas de Wuthering Waves"
      }
    },
    "planner": {
      "title": "Planificador de Ascensión",
      "description": "¡La calculadora más potente de Wuthering Waves para planear el nivel de ascensión de tus Resonadores, habilidades, y materiales de mejora!"
    },
    "support": {
      "title": "Soporte",
      "description": "¿Necesitas ayuda para descargar los datos de tus invocaciones en Wuthering Waves? ¿Quieres conocer como WuWa Tracker usa tus datos? ¡Ve las preguntas frecuentes de Wuwa Tracker aquí!"
    },
    "articles": {
      "title": "Artículos",
      "description": "¡Lee los últimos artículos y actualizaciones sobre Wuthering Waves, incluyendo guías, consejos, noticias, anuncios y más!"
    }
  },
  "config": {
    "navLinks": {
      "Tracker": "Seguidor",
      "Import Pulls": "Importar Invocaciones",
      "Global Statistics": "Estadísticas globales",
      "Wiki": "Wiki",
      "Characters": "Resonadores",
      "Weapons": "Armas",
      "Items": "Objetos",
      "Tools": "Herramientas",
      "Achievements Tracker": "Seguidor de Logros",
      "Ascension Planner": "Planificador de Ascensión",
      "Events": "Eventos",
      "Articles": "Artículos",
      "Old Site": "Sitio Antiguo"
    },
    "footer": {
      "links": {
        "Contact Us": "Contacta con Nosotros",
        "System Status": "Estado del sistema",
        "Help Translate": "Ayuda a traducir",
        "Privacy Policy": "Políticas de Privacidad",
        "Terms of Service": "Términos de servicio",
        "Company": "Empresa",
        "Resources": "Recursos",
        "Community": "Comunidad",
        "Affiliates": "Afiliados"
      }
    }
  }
}
